idem_bsd/conf.py
idem_bsd/version.py
idem_bsd/exec/bsd/init.py
idem_bsd/grains/bsd/defaults.py
idem_bsd/grains/bsd/init.py
idem_bsd/grains/bsd/hw/bios.py
idem_bsd/grains/bsd/hw/cpu.py
idem_bsd/grains/bsd/hw/disks.py
idem_bsd/grains/bsd/hw/gpu.py
idem_bsd/grains/bsd/hw/mem.py
idem_bsd/grains/bsd/net/gateway.py
idem_bsd/grains/bsd/net/interfaces.py
idem_bsd/grains/bsd/net/realm.py
idem_bsd/grains/bsd/os/arch.py
idem_bsd/grains/bsd/os/os.py
idem_bsd/states/bsd/init.py
idem_bsd-4.2.dist-info/METADATA
idem_bsd-4.2.dist-info/WHEEL
idem_bsd-4.2.dist-info/top_level.txt
idem_bsd-4.2.dist-info/RECORD
