Metadata-Version: 2.1
Name: idem-bsd
Version: 4.2
Summary: Vertical app merge components for Idem and grains support on BSD
Home-page: https://gitlab.com/saltstack/pop/idem-bsd
Author: Tyler Johnson
Author-email: tjohnson@saltstack.com
License: UNKNOWN
Platform: UNKNOWN
Classifier: Operating System :: POSIX :: BSD
Classifier: Operating System :: POSIX :: BSD :: FreeBSD
Classifier: Operating System :: POSIX :: BSD :: NetBSD
Classifier: Operating System :: POSIX :: BSD :: OpenBSD 
Classifier: Programming Language :: Python
Classifier: Programming Language :: Python :: 3.6
Classifier: Programming Language :: Python :: 3.7
Classifier: Programming Language :: Python :: 3.8
Classifier: Development Status :: 5 - Production/Stable
Requires-Python: >=3.6
Requires-Dist: grains-virt (>=3)
Requires-Dist: idem-posix (>=2.1)
Requires-Dist: ifcfg (>=0.16)
